sb_serializer/__init__.py
sb_serializer/hard_serializer.py
sb_serializer/naming.py
sb_serializer/utils.py
tests/naming_tests.py
tests/serializer_tests.py
sb_serializer-0.0.3.dist-info/LICENSE
sb_serializer-0.0.3.dist-info/METADATA
sb_serializer-0.0.3.dist-info/WHEEL
sb_serializer-0.0.3.dist-info/top_level.txt
sb_serializer-0.0.3.dist-info/RECORD
