Metadata-Version: 2.1
Name: sb-serializer
Version: 0.0.3
Summary: A json serializer and naming implementation
Author-email: Stephen Booth <stephen.booth.za@gmail.com>
Project-URL: homepage, https://github.com/sboothza/serializer
Classifier: Programming Language :: Python :: 3
Classifier: License :: OSI Approved :: MIT License
Classifier: Operating System :: OS Independent
Requires-Python: >=3.7
License-File: LICENSE
Requires-Dist: uuid ~=1.30
